hw/__init__.py
hw/cpu_reader.py
hw/dmidecode_reader.py
hw/lspci_reader.py
hw/etc/commands.json
phw-0.1.dist-info/LICENSE
phw-0.1.dist-info/METADATA
phw-0.1.dist-info/WHEEL
phw-0.1.dist-info/top_level.txt
phw-0.1.dist-info/RECORD
