Metadata-Version: 2.1
Name: phw
Version: 0.1
Summary: A lspci/lscpu/dmidecode cmd parser to get hardware info
Home-page: https://github.com/deskos-xp/pyHardware
Author: Karl Josef Wisdom
Author-email: k.j.hirner.wisdom@gmail.com
License: UNKNOWN
Platform: UNKNOWN
Classifier: Programming Language :: Python :: 3
Classifier: License :: OSI Approved :: GNU Lesser General Public License v3 or later (LGPLv3+)
Classifier: Operating System :: POSIX :: Linux
